Workbook

Sheet Inventario
A1: Codigo | B1: Articulo | C1: PrecioUnitario | D1: CantidadBodega
A2: KM001 | B2: Brochas (10 piezas) | C2: 6500 | D2: 24
A3: KM002 | B3: Paleta de sombras | C3: 10200 | D3: 28
A4: KM003 | B4: Iluminador | C4: 3500 | D4: 22
A5: KM004 | B5: Base | C5: 7300 | D5: 26
A6: KM005 | B6: Polvos translúcidos | C6: 6500 | D6: 25
A7: KM006 | B7: Polvos compactos | C7: 7000 | D7: 20
A8: KM007 | B8: Gel de cejas | C8: 2500 | D8: 30
A9: KM008 | B9: Gloss | C9: 200 | D9: 40
A10: KM009 | B10: Hidratante de labios | C10: 1800 | D10: 32
A11: KM010 | B11: Sellador de maquillaje | C11: 6300 | D11: 18
A12: KM011 | B12: Corrector | C12: 5500 | D12: 27
A13: KM012 | B13: Rímel | C13: 4800 | D13: 29
... A21: KM020 | B21: Primer | C21: 4800 | D21: 26

Sheet Factura
A1: Kissmake-up
A3: Factura No.: | B3: KM-000901 | D3: Cliente: | E3: Nombre del Cliente
A4: Fecha: | B4: 2025-10-30 | D4: Identificación: | E4: Cédula / N°
A6: Contacto: | B6: San José, CR • 2222-2222 • ventas@kissmakeup.cr
A10: Código | B10: Artículo | C10: Precio unitario | D10: Cantidad | E10: Importe
B11: =SI(A11="";"";BUSCARV(A11;Inventario!$A$2:$C$21;2;FALSO)) | C11: =SI(A11="";"";BUSCARV(A11;Inventario!$A$2:$C$21;3;FALSO)) | E11: =SI(O(C11="";D11="");"";C11*D11)
B12: =SI(A12="";"";BUSCARV(A12;Inventario!$A$2:$C$21;2;FALSO)) | C12: =SI(A12="";"";BUSCARV(A12;Inventario!$A$2:$C$21;3;FALSO)) | E12: =SI(O(C12="";D12="");"";C12*D12)
B13: =SI(A13="";"";BUSCARV(A13;Inventario!$A$2:$C$21;2;FALSO)) | C13: =SI(A13="";"";BUSCARV(A13;Inventario!$A$2:$C$21;3;FALSO)) | E13: =SI(O(C13="";D13="");"";C13*D13)
B14: =SI(A14="";"";BUSCARV(A14;Inventario!$A$2:$C$21;2;FALSO)) | C14: =SI(A14="";"";BUSCARV(A14;Inventario!$A$2:$C$21;3;FALSO)) | E14: =SI(O(C14="";D14="");"";C14*D14)
B15: =SI(A15="";"";BUSCARV(A15;Inventario!$A$2:$C$21;2;FALSO)) | C15: =SI(A15="";"";BUSCARV(A15;Inventario!$A$2:$C$21;3;FALSO)) | E15: =SI(O(C15="";D15="");"";C15*D15)
B16: =SI(A16="";"";BUSCARV(A16;Inventario!$A$2:$C$21;2;FALSO)) | C16: =SI(A16="";"";BUSCARV(A16;Inventario!$A$2:$C$21;3;FALSO)) | E16: =SI(O(C16="";D16="");"";C16*D16)
B17: =SI(A17="";"";BUSCARV(A17;Inventario!$A$2:$C$21;2;FALSO)) | C17: =SI(A17="";"";BUSCARV(A17;Inventario!$A$2:$C$21;3;FALSO)) | E17: =SI(O(C17="";D17="");"";C17*D17)
B18: =SI(A18="";"";BUSCARV(A18;Inventario!$A$2:$C$21;2;FALSO)) | C18: =SI(A18="";"";BUSCARV(A18;Inventario!$A$2:$C$21;3;FALSO)) | E18: =SI(O(C18="";D18="");"";C18*D18)
B19: =SI(A19="";"";BUSCARV(A19;Inventario!$A$2:$C$21;2;FALSO)) | C19: =SI(A19="";"";BUSCARV(A19;Inventario!$A$2:$C$21;3;FALSO)) | E19: =SI(O(C19="";D19="");"";C19*D19)
B20: =SI(A20="";"";BUSCARV(A20;Inventario!$A$2:$C$21;2;FALSO)) | C20: =SI(A20="";"";BUSCARV(A20;Inventario!$A$2:$C$21;3;FALSO)) | E20: =SI(O(C20="";D20="");"";C20*D20)
B21: =SI(A21="";"";BUSCARV(A21;Inventario!$A$2:$C$21;2;FALSO)) | C21: =SI(A21="";"";BUSCARV(A21;Inventario!$A$2:$C$21;3;FALSO)) | E21: =SI(O(C21="";D21="");"";C21*D21)
B22: =SI(A22="";"";BUSCARV(A22;Inventario!$A$2:$C$21;2;FALSO)) | C22: =SI(A22="";"";BUSCARV(A22;Inventario!$A$2:$C$21;3;FALSO)) | E22: =SI(O(C22="";D22="");"";C22*D22)
D24: Subtotal | E24: =SUMA(E11:E22)
D25: IVA (13%) | E25: =SI(E24="";"";E24*0.13)
D26: Total | E26: =SI(E24="";"";E24+E25)
