Workbook

Sheet Inventario
A1: Codigo | B1: Articulo | C1: PrecioUnitario | D1: CantidadBodega
A2: KM001 | B2: Brochas (10 piezas) | C2: 6500 | D2: 24
A3: KM002 | B3: Paleta de sombras | C3: 10200 | D3: 28
A4: KM003 | B4: Iluminador | C4: 3500 | D4: 22
A5: KM004 | B5: Base | C5: 7300 | D5: 26
A6: KM005 | B6: Polvos translúcidos | C6: 6500 | D6: 25
A7: KM006 | B7: Polvos compactos | C7: 7000 | D7: 20
A8: KM007 | B8: Gel de cejas | C8: 2500 | D8: 30
A9: KM008 | B9: Gloss | C9: 200 | D9: 40
A10: KM009 | B10: Hidratante de labios | C10: 1800 | D10: 32
A11: KM010 | B11: Sellador de maquillaje | C11: 6300 | D11: 18
A12: KM011 | B12: Corrector | C12: 5500 | D12: 27
A13: KM012 | B13: Rímel | C13: 4800 | D13: 29
... A21: KM020 | B21: Primer | C21: 4800 | D21: 26

Sheet Factura
A1: Kissmake-up
A2: San José, Costa Rica • 2222-2222 • ventas@kissmakeup.cr
A4: Factura No.: | B4: KM-000901 | D4: Cliente: | E4: Nombre del Cliente
A5: Fecha: | B5: 2025-10-30 | D5: Identificación: | E5: Cédula / N°
A10: Código | B10: Artículo | C10: Precio unitario | D10: Cantidad | E10: Importe
B11: =IF(A11="","",VLOOKUP(A11,Inventario!$A$2:$C$21,2,FALSE)) | C11: =IF(A11="","",VLOOKUP(A11,Inventario!$A$2:$C$21,3,FALSE)) | E11: =IF(OR(C11="",D11=""),"",C11*D11)
B12: =IF(A12="","",VLOOKUP(A12,Inventario!$A$2:$C$21,2,FALSE)) | C12: =IF(A12="","",VLOOKUP(A12,Inventario!$A$2:$C$21,3,FALSE)) | E12: =IF(OR(C12="",D12=""),"",C12*D12)
B13: =IF(A13="","",VLOOKUP(A13,Inventario!$A$2:$C$21,2,FALSE)) | C13: =IF(A13="","",VLOOKUP(A13,Inventario!$A$2:$C$21,3,FALSE)) | E13: =IF(OR(C13="",D13=""),"",C13*D13)
B14: =IF(A14="","",VLOOKUP(A14,Inventario!$A$2:$C$21,2,FALSE)) | C14: =IF(A14="","",VLOOKUP(A14,Inventario!$A$2:$C$21,3,FALSE)) | E14: =IF(OR(C14="",D14=""),"",C14*D14)
B15: =IF(A15="","",VLOOKUP(A15,Inventario!$A$2:$C$21,2,FALSE)) | C15: =IF(A15="","",VLOOKUP(A15,Inventario!$A$2:$C$21,3,FALSE)) | E15: =IF(OR(C15="",D15=""),"",C15*D15)
B16: =IF(A16="","",VLOOKUP(A16,Inventario!$A$2:$C$21,2,FALSE)) | C16: =IF(A16="","",VLOOKUP(A16,Inventario!$A$2:$C$21,3,FALSE)) | E16: =IF(OR(C16="",D16=""),"",C16*D16)
B17: =IF(A17="","",VLOOKUP(A17,Inventario!$A$2:$C$21,2,FALSE)) | C17: =IF(A17="","",VLOOKUP(A17,Inventario!$A$2:$C$21,3,FALSE)) | E17: =IF(OR(C17="",D17=""),"",C17*D17)
B18: =IF(A18="","",VLOOKUP(A18,Inventario!$A$2:$C$21,2,FALSE)) | C18: =IF(A18="","",VLOOKUP(A18,Inventario!$A$2:$C$21,3,FALSE)) | E18: =IF(OR(C18="",D18=""),"",C18*D18)
B19: =IF(A19="","",VLOOKUP(A19,Inventario!$A$2:$C$21,2,FALSE)) | C19: =IF(A19="","",VLOOKUP(A19,Inventario!$A$2:$C$21,3,FALSE)) | E19: =IF(OR(C19="",D19=""),"",C19*D19)
B20: =IF(A20="","",VLOOKUP(A20,Inventario!$A$2:$C$21,2,FALSE)) | C20: =IF(A20="","",VLOOKUP(A20,Inventario!$A$2:$C$21,3,FALSE)) | E20: =IF(OR(C20="",D20=""),"",C20*D20)
D22: Subtotal | E22: =SUM(E11:E20)
D23: IVA (13%) | E23: =IF(E22="","",E22*0.13)
D24: Total | E24: =IF(E22="","",E22+E23)
